autora/experimentalist/extrapolation/__init__.py
autora_experimentalist_extrapolation-1.0.1.dist-info/LICENSE
autora_experimentalist_extrapolation-1.0.1.dist-info/METADATA
autora_experimentalist_extrapolation-1.0.1.dist-info/WHEEL
autora_experimentalist_extrapolation-1.0.1.dist-info/top_level.txt
autora_experimentalist_extrapolation-1.0.1.dist-info/RECORD
